louvainsplit/__init__.py
louvainsplit/feature_extraction.py
louvainsplit/louvain_algorithm.py
louvainsplit/tests/__init__.py
louvainsplit/tests/test_louvain_algorithm.py
louvainsplit-0.2.0.4.dist-info/LICENCE
louvainsplit-0.2.0.4.dist-info/METADATA
louvainsplit-0.2.0.4.dist-info/WHEEL
louvainsplit-0.2.0.4.dist-info/top_level.txt
louvainsplit-0.2.0.4.dist-info/RECORD
